django_unused_context/__init__.py
django_unused_context/middleware.py
tests/__init__.py
tests/settings.py
tests/test_views.py
tests/urls.py
tests/views.py
django_unused_context-0.1.4.dist-info/LICENSE
django_unused_context-0.1.4.dist-info/METADATA
django_unused_context-0.1.4.dist-info/WHEEL
django_unused_context-0.1.4.dist-info/top_level.txt
django_unused_context-0.1.4.dist-info/RECORD
