Metadata-Version: 2.1
Name: django-unused-context
Version: 0.1.4
Summary: A Django middleware to trigger warnings when context keys are not used in a template.
Home-page: https://github.com/DJBarnes/django-unused-context
Author: David Barnes
Author-email: David Barnes <barnesdavidj@gmail.com>
License: MIT License        
Project-URL: Homepage, https://github.com/djbarnes/django-unused-context
Keywords: context,debug,django,unused
Classifier: Environment :: Web Environment
Classifier: Framework :: Django
Classifier: Framework :: Django :: 3
Classifier: Framework :: Django :: 3.0
Classifier: Framework :: Django :: 3.1
Classifier: Framework :: Django :: 3.2
Classifier: Framework :: Django :: 4
Classifier: Framework :: Django :: 4.0
Classifier: Intended Audience :: Developers
Classifier: License :: OSI Approved :: MIT License
Classifier: Operating System :: OS Independent
Classifier: Programming Language :: Python
Classifier: Programming Language :: Python :: 3
Classifier: Programming Language :: Python :: 3 :: Only
Classifier: Programming Language :: Python :: 3.7
Classifier: Programming Language :: Python :: 3.8
Classifier: Programming Language :: Python :: 3.9
Classifier: Programming Language :: Python :: 3.10
Classifier: Topic :: Internet :: WWW/HTTP
Classifier: Topic :: Internet :: WWW/HTTP :: Dynamic Content
Requires-Python: >=3.7
License-File: LICENSE
Requires-Dist: django (>=3.0.0)
Provides-Extra: dev
Requires-Dist: black ; extra == 'dev'
Requires-Dist: coverage ; extra == 'dev'
Requires-Dist: pip-tools ; extra == 'dev'
Requires-Dist: pylint ; extra == 'dev'
Requires-Dist: pylint-django ; extra == 'dev'
Provides-Extra: doc
Requires-Dist: doc8 ; extra == 'doc'
Requires-Dist: esbonio ; extra == 'doc'
Requires-Dist: pip-tools ; extra == 'doc'
Requires-Dist: rstcheck ; extra == 'doc'
Requires-Dist: sphinx ; extra == 'doc'
Requires-Dist: sphinx-autobuild ; extra == 'doc'
Requires-Dist: sphinx-rtd-theme ; extra == 'doc'
